{"cameraMode":{"drawMode":0,"name":"Shaded","section":"Shading Mode"},"sceneLighting":true,"audioPlay":false,"sceneViewState":{"m_AlwaysRefresh":false,"showFog":true,"showSkybox":true,"showFlares":true,"showImageEffects":true,"showParticleSystems":true,"showVisualEffectGraphs":true,"m_FxEnabled":true},"in2DMode":false,"pivot":{"x":0.0,"y":1.614999771118164,"z":-2.1299989223480226},"rotation":{"x":-0.014994848519563675,"y":-0.024880442768335344,"z":0.00037860972224734724,"w":-0.9995883703231812},"size":2.5590851306915285,"orthographic":true}